sadice/__init__.py
sadice/loss.py
sadice-0.1.3.dist-info/LICENSE
sadice-0.1.3.dist-info/WHEEL
sadice-0.1.3.dist-info/METADATA
sadice-0.1.3.dist-info/RECORD
