Metadata-Version: 2.1
Name: sadice
Version: 0.1.3
Summary: Self-adjusting Dice Loss implementation
Home-page: https://github.com/fursovia/self-adj-dice
License: Apache-2.0
Author: Ivan Fursov
Author-email: fursovia@gmail.com
Requires-Python: >=3.6.1,<4.0.0
Classifier: License :: OSI Approved :: Apache Software License
Classifier: Programming Language :: Python :: 3
Classifier: Programming Language :: Python :: 3.7
Classifier: Programming Language :: Python :: 3.8
Requires-Dist: torch (>=1.0.0,<2.0.0)
Project-URL: Repository, https://github.com/fursovia/self-adj-dice
